todo_cli/__init__.py
todo_cli/cli.py
todo_cli/config.py
todo_cli/models.py
todo_cli/service.py
todo_cli/storage.py
todo_cli_crazychief-0.1.1.dist-info/METADATA
todo_cli_crazychief-0.1.1.dist-info/WHEEL
todo_cli_crazychief-0.1.1.dist-info/entry_points.txt
todo_cli_crazychief-0.1.1.dist-info/licenses/LICENSE.md
todo_cli_crazychief-0.1.1.dist-info/RECORD
