Metadata-Version: 2.4
Name: todo-cli_CrazyChief
Version: 0.1.1
Summary: A command-line TODO list application
Project-URL: Homepage, https://github.com/CrazyChief/todo-cli
Project-URL: Bug Tracker, https://github.com/CrazyChief/todo-cli/issues
Author-email: Dmitry Danilov <danilovdmitry94@gmail.com>
License-File: LICENSE.md
Classifier: License :: OSI Approved :: MIT License
Classifier: Operating System :: OS Independent
Classifier: Programming Language :: Python :: 3
Requires-Python: >=3.6
Requires-Dist: click
Requires-Dist: pydantic
Requires-Dist: python-dotenv
